addok/__init__.py
addok/autocomplete.py
addok/batch.py
addok/core.py
addok/db.py
addok/ds.py
addok/fuzzy.py
addok/hooks.py
addok/pairs.py
addok/pytest.py
addok/shell.py
addok/bin/__init__.py
addok/config/__init__.py
addok/config/default.py
addok/config/test.py
addok/helpers/__init__.py
addok/helpers/collectors.py
addok/helpers/formatters.py
addok/helpers/index.py
addok/helpers/keys.py
addok/helpers/results.py
addok/helpers/scripts.py
addok/helpers/search.py
addok/helpers/serializers.py
addok/helpers/text.py
addok/helpers/lua/manual_scan.lua
addok/helpers/lua/order_by_frequency.lua
addok/helpers/lua/order_by_max_score.lua
addok/helpers/lua/zinter.lua
addok/http/__init__.py
addok/http/base.py
addok/http/wsgi.py
addok-1.3.1.dist-info/licenses/LICENSE
addok-1.3.1.dist-info/METADATA
addok-1.3.1.dist-info/WHEEL
addok-1.3.1.dist-info/entry_points.txt
addok-1.3.1.dist-info/top_level.txt
addok-1.3.1.dist-info/RECORD
