Metadata-Version: 2.4
Name: addok
Version: 1.3.1
Summary: Search engine for address. Only address.
Author-email: Yohan Boniface <yohan.boniface@data.gouv.fr>
License-Expression: MIT
Project-URL: Homepage, https://github.com/addok/addok
Keywords: address,openstreetmap,geocoding
Classifier: Development Status :: 5 - Production/Stable
Classifier: Intended Audience :: Developers
Classifier: Topic :: Scientific/Engineering :: GIS
Classifier: Programming Language :: Python :: 3.9
Classifier: Programming Language :: Python :: 3.10
Classifier: Programming Language :: Python :: 3.11
Classifier: Programming Language :: Python :: 3.12
Classifier: Programming Language :: Python :: 3.13
Classifier: Programming Language :: Python :: 3.14
Requires-Python: >=3.9
License-File: LICENSE
Requires-Dist: falcon==4.0.2
Requires-Dist: hashids==1.3.1
Requires-Dist: editdistance==0.8.1
Requires-Dist: ngram==4.0.3
Requires-Dist: progressist==0.1.0
Requires-Dist: python-geohash==0.8.5
Requires-Dist: redis==6.4.0
Requires-Dist: unidecode==1.4.0
Requires-Dist: gnureadline==8.2.13; sys_platform == "darwin"
Provides-Extra: perf
Requires-Dist: hiredis==3.3.0; extra == "perf"
Provides-Extra: dev
Requires-Dist: pytest~=8.3; extra == "dev"
Requires-Dist: pytest-cov~=6.1; extra == "dev"
Requires-Dist: mkdocs==1.4.3; extra == "dev"
Requires-Dist: build~=1.2; extra == "dev"
Requires-Dist: twine==6.1.0; extra == "dev"
Requires-Dist: hiredis==3.3.0; extra == "dev"
Dynamic: license-file
